appletalk/Finder.py
appletalk/SystemEvents.py
appletalk/__init__.py
appletalk/activitymonitor.py
appletalk/apps.py
appletalk/chrome.py
appletalk/clipboard.py
appletalk/contacts.py
appletalk/display.py
appletalk/init.py
appletalk/mail.py
appletalk/quicktime.py
appletalk/syssettings.py
appletalk/terminal.py
appletalk/textedit.py
appletalk-0.0.6.dist-info/licenses/LICENSE
appletalk-0.0.6.dist-info/METADATA
appletalk-0.0.6.dist-info/WHEEL
appletalk-0.0.6.dist-info/top_level.txt
appletalk-0.0.6.dist-info/RECORD
