Metadata-Version: 2.4
Name: appletalk
Version: 0.0.6
Summary: a Python library for macOS AppleScript dialogs and notifications
Home-page: 
Author: Annes
Classifier: Programming Language :: Python :: 3
Classifier: Operating System :: OS Independent
Requires-Python: >=3.7
License-File: LICENSE
Dynamic: author
Dynamic: classifier
Dynamic: description
Dynamic: description-content-type
Dynamic: license-file
Dynamic: requires-python
Dynamic: summary
